{
  "id": "task-001",
  "description": "Create `palindrome.py` at the repo root with `is_palindrome(s: str) -> bool` returning True iff s reads the same forwards and backwards (case-insensitive, non-alphanumeric chars ignored). Existing tests in tests/test_palindrome.py must pass.",
  "repo": "/Users/matteo/projects/catallaxy/repos/playground",
  "base_branch": "main",
  "review_fee": 2000,
  "deterministic_checks": [
    {
      "type": "command",
      "cmd": "python3 -m unittest discover tests",
      "must_pass": true
    }
  ],
  "subjective_criteria": "Idiomatic, Unicode-safe.",
  "status": "expired",
  "posted_by": "operator",
  "posted_at": "2026-05-01T15:04:13.881Z",
  "deadline_at": "2026-05-01T15:09:13.881Z"
}